CHANGELOG.txt
LICENSE
MANIFEST.in
README.rst
setup.py
tests.py
requirements/base.txt
requirements/test.txt
serialkiller_plugins.egg-info/PKG-INFO
serialkiller_plugins.egg-info/SOURCES.txt
serialkiller_plugins.egg-info/dependency_links.txt
serialkiller_plugins.egg-info/not-zip-safe
serialkiller_plugins.egg-info/requires.txt
serialkiller_plugins.egg-info/top_level.txt
skplugins/__init__.py
skplugins/examples.py
skplugins/energy/__init__.py
skplugins/energy/teleinfo.py
skplugins/network/__init__.py
skplugins/network/ping.py
skplugins/system/__init__.py
skplugins/system/process.py
skplugins/weather/__init__.py
skplugins/weather/skmetar.py
skplugins/weather/sunshine.py
skplugins/weather/vigimeteo.py