Metadata-Version: 1.1
Name: serialkiller-plugins
Version: 0.0.2
Summary: Plugins for serialkiller project
Home-page: https://github.com/badele/serialkiller-plugins
Author: Bruno Adelé
Author-email: Bruno Adelé <bruno@adele.im>
License: GPL
Platform: UNKNOWN
Classifier: Programming Language :: Python
